README.md
setup.cfg
setup.py
file_gcd/__init__.py
file_gcd/__main__.py
file_gcd/gen_random_table.py
file_gcd/test1.csv
file_gcd/test2.csv
file_gcd.egg-info/PKG-INFO
file_gcd.egg-info/SOURCES.txt
file_gcd.egg-info/dependency_links.txt
file_gcd.egg-info/requires.txt
file_gcd.egg-info/top_level.txt