Metadata-Version: 2.1
Name: file_gcd
Version: 0.0.1
Summary: A toy model to consume file input and output with simple calculation logic
Home-page: https://github.com/danieltuzes/file_gcd
Author: Daniel Tuzes
Author-email: tuzesdaniel@gmail.com
Project-URL: Source, https://github.com/danieltuzes/file_gcd
Project-URL: Documentation, https://github.com/danieltuzes/file_gcd/blob/main/README.md
Keywords: python,packaging,pip
Classifier: Programming Language :: Python :: 3.9
Classifier: Programming Language :: Python :: 3.10
Classifier: Programming Language :: Python :: 3.11
Requires-Python: >=3.9
Requires-Dist: pandas
